views_dataviz/__init__.py
views_dataviz-0.11.0.dist-info/WHEEL
views_dataviz-0.11.0.dist-info/METADATA
views_dataviz-0.11.0.dist-info/RECORD
